andperf/__init__.py
andperf/_config.py
andperf/_util.py
andperf/andperf.py
andperf/gfxinfo.py
andperf/meminfo.py
andperf/stat_thread.py
andperf-0.0.3.dist-info/LICENSE
andperf-0.0.3.dist-info/METADATA
andperf-0.0.3.dist-info/WHEEL
andperf-0.0.3.dist-info/entry_points.txt
andperf-0.0.3.dist-info/top_level.txt
andperf-0.0.3.dist-info/RECORD
