Metadata-Version: 2.1
Name: andperf
Version: 0.0.3
Summary: Android 性能调优工具
Home-page: https://github.com/weixinfree/AndPerf
Author: WangWei
Author-email: 2317073226@qq.com
License: UNKNOWN
Platform: UNKNOWN
Classifier: Programming Language :: Python :: 3
Classifier: License :: OSI Approved :: MIT License
Classifier: Operating System :: OS Independent
Requires-Dist: matplotlib (==3.0.0)
Requires-Dist: numpy (==1.15.1)
Requires-Dist: pandas (==0.23.4)
Requires-Dist: fire (==0.1.3)
